Metadata-Version: 1.0
Name: jeff-distributions
Version: 0.1
Summary: Gaussian distributions
Home-page: UNKNOWN
Author: Jeff Zhong
Author-email: jeffwzhong@gmail.com
License: UNKNOWN
Platform: UNKNOWN
